meth5/__init__.py
meth5/meth5.py
meth5/sparse_matrix.py
meth5-0.2.5.dev1.dist-info/LICENSE
meth5-0.2.5.dev1.dist-info/METADATA
meth5-0.2.5.dev1.dist-info/WHEEL
meth5-0.2.5.dev1.dist-info/entry_points.txt
meth5-0.2.5.dev1.dist-info/top_level.txt
meth5-0.2.5.dev1.dist-info/RECORD
