Metadata-Version: 2.1
Name: meth5
Version: 0.2.5.dev1
Summary: HDF5 based file format for storage, retrieval, and analysis of modification predictions from Nanopore
Home-page: https://github.com/snajder-r/meth5format
Author: Rene Snajder
Author-email: r.snajder@dkfz-heidelberg.de
License: MIT
Platform: UNKNOWN
Classifier: Development Status :: 4 - Beta
Classifier: Intended Audience :: Science/Research
Classifier: Topic :: Scientific/Engineering :: Bio-Informatics
Classifier: License :: OSI Approved :: MIT License
Classifier: Programming Language :: Python :: 3
Requires-Python: >=3.7
Requires-Dist: numpy (>=1.19.2)
Requires-Dist: scipy (==1.4.1)
Requires-Dist: pandas (>=1.1.3)
Requires-Dist: h5py (>=2.10.0)
